pybasic/__init__.py
pybasic/shading_correction.py
pybasic_illumination_correction-0.1.1.dist-info/entry_points.txt
pybasic_illumination_correction-0.1.1.dist-info/WHEEL
pybasic_illumination_correction-0.1.1.dist-info/METADATA
pybasic_illumination_correction-0.1.1.dist-info/RECORD
